{
  "generated_at": "2026-02-16T05:24:40.690951+00:00",
  "tag": "Delivered",
  "dedup_enabled": false,
  "dedup_days": 0,
  "count": 149,
  "items": [
    {
      "tracking_number": "JJD149990121180201329",
      "carrier_slug": "dhlparcel-nl",
      "courier_name": "DHL Parcel NL",
      "status_tag": "Delivered",
      "title": "JJD149990121180201329",
      "order_id": "6001592576",
      "sales_office_id": "",
      "source": "csv_importer",
      "custom_fields": {},
      "last_checkpoint_id": "",
      "last_checkpoint_time": "2026-02-12T13:12:00+01:00",
      "last_checkpoint_location": "",
      "updated_at": "2026-02-16T00:43:16+00:00"
    },
    {
      "tracking_number": "JJD149990121180201224",
      "carrier_slug": "dhlparcel-nl",
      "courier_name": "DHL Parcel NL",
      "status_tag": "Delivered",
      "title": "JJD149990121180201224",
      "order_id": "6001592721",
      "sales_office_id": "",
      "source": "csv_importer",
      "custom_fields": {},
      "last_checkpoint_id": "",
      "last_checkpoint_time": "2026-02-09T16:55:00+01:00",
      "last_checkpoint_location": "",
      "updated_at": "2026-02-16T00:43:15+00:00"
    },
    {
      "tracking_number": "JJD149990121180200714",
      "carrier_slug": "dhlparcel-nl",
      "courier_name": "DHL Parcel NL",
      "status_tag": "Delivered",
      "title": "JJD149990121180200714",
      "order_id": "6001592999",
      "sales_office_id": "",
      "source": "csv_importer",
      "custom_fields": {},
      "last_checkpoint_id": "",
      "last_checkpoint_time": "2026-02-12T13:12:00+01:00",
      "last_checkpoint_location": "",
      "updated_at": "2026-02-16T00:43:17+00:00"
    },
    {
      "tracking_number": "JJD149990121180201219",
      "carrier_slug": "dhlparcel-nl",
      "courier_name": "DHL Parcel NL",
      "status_tag": "Delivered",
      "title": "JJD149990121180201219",
      "order_id": "6001592769",
      "sales_office_id": "",
      "source": "csv_importer",
      "custom_fields": {},
      "last_checkpoint_id": "",
      "last_checkpoint_time": "2026-02-13T10:25:00+01:00",
      "last_checkpoint_location": "",
      "updated_at": "2026-02-16T04:43:16+00:00"
    },
    {
      "tracking_number": "JJD149990121180201655",
      "carrier_slug": "dhlparcel-nl",
      "courier_name": "DHL Parcel NL",
      "status_tag": "Delivered",
      "title": "JJD149990121180201655",
      "order_id": "6001592089",
      "sales_office_id": "",
      "source": "csv_importer",
      "custom_fields": {},
      "last_checkpoint_id": "",
      "last_checkpoint_time": "2026-02-12T13:12:00+01:00",
      "last_checkpoint_location": "",
      "updated_at": "2026-02-16T00:43:15+00:00"
    },
    {
      "tracking_number": "JJD149990121180200821",
      "carrier_slug": "dhlparcel-nl",
      "courier_name": "DHL Parcel NL",
      "status_tag": "Delivered",
      "title": "JJD149990121180200821",
      "order_id": "6001592890",
      "sales_office_id": "",
      "source": "csv_importer",
      "custom_fields": {},
      "last_checkpoint_id": "",
      "last_checkpoint_time": "2026-02-10T13:04:00+01:00",
      "last_checkpoint_location": "",
      "updated_at": "2026-02-16T00:43:16+00:00"
    },
    {
      "tracking_number": "JJD149990121180201154",
      "carrier_slug": "dhlparcel-nl",
      "courier_name": "DHL Parcel NL",
      "status_tag": "Delivered",
      "title": "JJD149990121180201154",
      "order_id": "6001592797",
      "sales_office_id": "",
      "source": "csv_importer",
      "custom_fields": {},
      "last_checkpoint_id": "",
      "last_checkpoint_time": "2026-02-12T13:12:00+01:00",
      "last_checkpoint_location": "",
      "updated_at": "2026-02-16T00:43:16+00:00"
    },
    {
      "tracking_number": "JJD149990121180201418",
      "carrier_slug": "dhlparcel-nl",
      "courier_name": "DHL Parcel NL",
      "status_tag": "Delivered",
      "title": "JJD149990121180201418",
      "order_id": "6001592477",
      "sales_office_id": "",
      "source": "csv_importer",
      "custom_fields": {},
      "last_checkpoint_id": "",
      "last_checkpoint_time": "2026-02-10T13:04:00+01:00",
      "last_checkpoint_location": "",
      "updated_at": "2026-02-16T00:43:14+00:00"
    },
    {
      "tracking_number": "JJD149990121180201397",
      "carrier_slug": "dhlparcel-nl",
      "courier_name": "DHL Parcel NL",
      "status_tag": "Delivered",
      "title": "JJD149990121180201397",
      "order_id": "6001592501",
      "sales_office_id": "",
      "source": "csv_importer",
      "custom_fields": {},
      "last_checkpoint_id": "",
      "last_checkpoint_time": "2026-02-10T13:04:00+01:00",
      "last_checkpoint_location": "",
      "updated_at": "2026-02-16T00:43:16+00:00"
    },
    {
      "tracking_number": "JJD149990121180201399",
      "carrier_slug": "dhlparcel-nl",
      "courier_name": "DHL Parcel NL",
      "status_tag": "Delivered",
      "title": "JJD149990121180201399",
      "order_id": "6001592526",
      "sales_office_id": "",
      "source": "csv_importer",
      "custom_fields": {},
      "last_checkpoint_id": "",
      "last_checkpoint_time": "2026-02-10T13:04:00+01:00",
      "last_checkpoint_location": "",
      "updated_at": "2026-02-16T00:43:14+00:00"
    },
    {
      "tracking_number": "JJD149990121180201694",
      "carrier_slug": "dhlparcel-nl",
      "courier_name": "DHL Parcel NL",
      "status_tag": "Delivered",
      "title": "JJD149990121180201694",
      "order_id": "6001592070",
      "sales_office_id": "",
      "source": "csv_importer",
      "custom_fields": {},
      "last_checkpoint_id": "",
      "last_checkpoint_time": "2026-02-11T13:17:00+01:00",
      "last_checkpoint_location": "",
      "updated_at": "2026-02-16T00:43:16+00:00"
    },
    {
      "tracking_number": "CY427796411DE",
      "carrier_slug": "dhl-germany",
      "courier_name": "Deutsche Post DHL",
      "status_tag": "Delivered",
      "title": "CY427796411DE",
      "order_id": "6001593880",
      "sales_office_id": "",
      "source": "csv_importer",
      "custom_fields": {},
      "last_checkpoint_id": "",
      "last_checkpoint_time": "2026-02-06T12:58:00+01:00",
      "last_checkpoint_location": "Netherlands",
      "updated_at": "2026-02-16T00:43:15+00:00"
    },
    {
      "tracking_number": "JJD149990121180201266",
      "carrier_slug": "dhlparcel-nl",
      "courier_name": "DHL Parcel NL",
      "status_tag": "Delivered",
      "title": "JJD149990121180201266",
      "order_id": "6001592668",
      "sales_office_id": "",
      "source": "csv_importer",
      "custom_fields": {},
      "last_checkpoint_id": "",
      "last_checkpoint_time": "2026-02-13T10:25:00+01:00",
      "last_checkpoint_location": "",
      "updated_at": "2026-02-16T04:43:15+00:00"
    },
    {
      "tracking_number": "66033117400902",
      "carrier_slug": "hermes-de",
      "courier_name": "Hermes Germany",
      "status_tag": "Delivered",
      "title": "66033117400902",
      "order_id": "6001608778",
      "sales_office_id": "",
      "source": "csv_importer",
      "custom_fields": {},
      "last_checkpoint_id": "",
      "last_checkpoint_time": "2026-02-06T11:53:19+01:00",
      "last_checkpoint_location": "Germany",
      "updated_at": "2026-02-16T00:43:15+00:00"
    },
    {
      "tracking_number": "JJD149990121180183905",
      "carrier_slug": "dhlparcel-nl",
      "courier_name": "DHL Parcel NL",
      "status_tag": "Delivered",
      "title": "JJD149990121180183905",
      "order_id": "6001532469",
      "sales_office_id": "",
      "source": "csv_importer",
      "custom_fields": {},
      "last_checkpoint_id": "",
      "last_checkpoint_time": "2026-01-27T12:35:00+01:00",
      "last_checkpoint_location": "",
      "updated_at": "2026-02-16T00:43:17+00:00"
    },
    {
      "tracking_number": "05222006537010",
      "carrier_slug": "dpd",
      "courier_name": "DPD",
      "status_tag": "Delivered",
      "title": "05222006537010",
      "order_id": "6001594803",
      "sales_office_id": "",
      "source": "csv_importer",
      "custom_fields": {},
      "last_checkpoint_id": "",
      "last_checkpoint_time": "2026-02-06T16:01:43+01:00",
      "last_checkpoint_location": "Taulov, DK, Denmark",
      "updated_at": "2026-02-16T00:43:17+00:00"
    },
    {
      "tracking_number": "JJD149990121180201533",
      "carrier_slug": "dhlparcel-nl",
      "courier_name": "DHL Parcel NL",
      "status_tag": "Delivered",
      "title": "JJD149990121180201533",
      "order_id": "6001592195",
      "sales_office_id": "",
      "source": "csv_importer",
      "custom_fields": {},
      "last_checkpoint_id": "",
      "last_checkpoint_time": "2026-02-11T13:17:00+01:00",
      "last_checkpoint_location": "",
      "updated_at": "2026-02-16T00:43:15+00:00"
    },
    {
      "tracking_number": "JJD149990121180203322",
      "carrier_slug": "dhlparcel-nl",
      "courier_name": "DHL Parcel NL",
      "status_tag": "Delivered",
      "title": "JJD149990121180203322",
      "order_id": "6001600261",
      "sales_office_id": "",
      "source": "csv_importer",
      "custom_fields": {},
      "last_checkpoint_id": "",
      "last_checkpoint_time": "2026-02-12T13:12:00+01:00",
      "last_checkpoint_location": "",
      "updated_at": "2026-02-16T00:43:14+00:00"
    },
    {
      "tracking_number": "JJD149990121180204792",
      "carrier_slug": "dhlparcel-nl",
      "courier_name": "DHL Parcel NL",
      "status_tag": "Delivered",
      "title": "JJD149990121180204792",
      "order_id": "6001607977",
      "sales_office_id": "",
      "source": "csv_importer",
      "custom_fields": {},
      "last_checkpoint_id": "",
      "last_checkpoint_time": "2026-02-12T13:12:00+01:00",
      "last_checkpoint_location": "",
      "updated_at": "2026-02-16T00:43:14+00:00"
    },
    {
      "tracking_number": "JJD149990121180205005",
      "carrier_slug": "dhlparcel-nl",
      "courier_name": "DHL Parcel NL",
      "status_tag": "Delivered",
      "title": "JJD149990121180205005",
      "order_id": "6001607934",
      "sales_office_id": "",
      "source": "csv_importer",
      "custom_fields": {},
      "last_checkpoint_id": "",
      "last_checkpoint_time": "2026-02-12T13:12:00+01:00",
      "last_checkpoint_location": "",
      "updated_at": "2026-02-16T00:43:14+00:00"
    },
    {
      "tracking_number": "JJD149990121180203381",
      "carrier_slug": "dhlparcel-nl",
      "courier_name": "DHL Parcel NL",
      "status_tag": "Delivered",
      "title": "JJD149990121180203381",
      "order_id": "6001600215",
      "sales_office_id": "",
      "source": "csv_importer",
      "custom_fields": {},
      "last_checkpoint_id": "",
      "last_checkpoint_time": "2026-02-12T13:12:00+01:00",
      "last_checkpoint_location": "",
      "updated_at": "2026-02-16T00:43:14+00:00"
    },
    {
      "tracking_number": "JJD149990121180204491",
      "carrier_slug": "dhlparcel-nl",
      "courier_name": "DHL Parcel NL",
      "status_tag": "Delivered",
      "title": "JJD149990121180204491",
      "order_id": "6001598993",
      "sales_office_id": "",
      "source": "csv_importer",
      "custom_fields": {},
      "last_checkpoint_id": "",
      "last_checkpoint_time": "2026-02-13T10:25:00+01:00",
      "last_checkpoint_location": "",
      "updated_at": "2026-02-16T04:43:15+00:00"
    },
    {
      "tracking_number": "JJD149990121180204508",
      "carrier_slug": "dhlparcel-nl",
      "courier_name": "DHL Parcel NL",
      "status_tag": "Delivered",
      "title": "JJD149990121180204508",
      "order_id": "6001598968",
      "sales_office_id": "",
      "source": "csv_importer",
      "custom_fields": {},
      "last_checkpoint_id": "",
      "last_checkpoint_time": "2026-02-13T10:25:00+01:00",
      "last_checkpoint_location": "",
      "updated_at": "2026-02-16T04:43:15+00:00"
    },
    {
      "tracking_number": "JJD149990121180204447",
      "carrier_slug": "dhlparcel-nl",
      "courier_name": "DHL Parcel NL",
      "status_tag": "Delivered",
      "title": "JJD149990121180204447",
      "order_id": "6001598995",
      "sales_office_id": "",
      "source": "csv_importer",
      "custom_fields": {},
      "last_checkpoint_id": "",
      "last_checkpoint_time": "2026-02-12T13:12:00+01:00",
      "last_checkpoint_location": "",
      "updated_at": "2026-02-16T00:43:13+00:00"
    },
    {
      "tracking_number": "JJD149990121180203012",
      "carrier_slug": "dhlparcel-nl",
      "courier_name": "DHL Parcel NL",
      "status_tag": "Delivered",
      "title": "JJD149990121180203012",
      "order_id": "6001614228",
      "sales_office_id": "",
      "source": "csv_importer",
      "custom_fields": {},
      "last_checkpoint_id": "",
      "last_checkpoint_time": "2026-02-11T13:17:00+01:00",
      "last_checkpoint_location": "",
      "updated_at": "2026-02-16T00:43:17+00:00"
    },
    {
      "tracking_number": "JJD149990121180202511",
      "carrier_slug": "dhlparcel-nl",
      "courier_name": "DHL Parcel NL",
      "status_tag": "Delivered",
      "title": "JJD149990121180202511",
      "order_id": "6001608849",
      "sales_office_id": "",
      "source": "csv_importer",
      "custom_fields": {},
      "last_checkpoint_id": "",
      "last_checkpoint_time": "2026-02-11T13:17:00+01:00",
      "last_checkpoint_location": "",
      "updated_at": "2026-02-16T00:43:16+00:00"
    },
    {
      "tracking_number": "JJD149990121180203420",
      "carrier_slug": "dhlparcel-nl",
      "courier_name": "DHL Parcel NL",
      "status_tag": "Delivered",
      "title": "JJD149990121180203420",
      "order_id": "6001600179",
      "sales_office_id": "",
      "source": "csv_importer",
      "custom_fields": {},
      "last_checkpoint_id": "",
      "last_checkpoint_time": "2026-02-13T10:25:00+01:00",
      "last_checkpoint_location": "",
      "updated_at": "2026-02-16T04:43:14+00:00"
    },
    {
      "tracking_number": "JJD149990121180203335",
      "carrier_slug": "dhlparcel-nl",
      "courier_name": "DHL Parcel NL",
      "status_tag": "Delivered",
      "title": "JJD149990121180203335",
      "order_id": "6001600252",
      "sales_office_id": "",
      "source": "csv_importer",
      "custom_fields": {},
      "last_checkpoint_id": "",
      "last_checkpoint_time": "2026-02-13T10:25:00+01:00",
      "last_checkpoint_location": "",
      "updated_at": "2026-02-16T04:43:14+00:00"
    },
    {
      "tracking_number": "JJD149990121180203702",
      "carrier_slug": "dhlparcel-nl",
      "courier_name": "DHL Parcel NL",
      "status_tag": "Delivered",
      "title": "JJD149990121180203702",
      "order_id": "6001599820",
      "sales_office_id": "",
      "source": "csv_importer",
      "custom_fields": {},
      "last_checkpoint_id": "",
      "last_checkpoint_time": "2026-02-12T13:12:00+01:00",
      "last_checkpoint_location": "",
      "updated_at": "2026-02-16T00:43:15+00:00"
    },
    {
      "tracking_number": "JJD149990121180202649",
      "carrier_slug": "dhlparcel-nl",
      "courier_name": "DHL Parcel NL",
      "status_tag": "Delivered",
      "title": "JJD149990121180202649",
      "order_id": "6001613904",
      "sales_office_id": "",
      "source": "csv_importer",
      "custom_fields": {},
      "last_checkpoint_id": "",
      "last_checkpoint_time": "2026-02-12T13:12:00+01:00",
      "last_checkpoint_location": "",
      "updated_at": "2026-02-16T00:43:14+00:00"
    },
    {
      "tracking_number": "JJD149990121180203173",
      "carrier_slug": "dhlparcel-nl",
      "courier_name": "DHL Parcel NL",
      "status_tag": "Delivered",
      "title": "JJD149990121180203173",
      "order_id": "6001614277",
      "sales_office_id": "",
      "source": "csv_importer",
      "custom_fields": {},
      "last_checkpoint_id": "",
      "last_checkpoint_time": "2026-02-13T10:25:00+01:00",
      "last_checkpoint_location": "",
      "updated_at": "2026-02-16T04:43:16+00:00"
    },
    {
      "tracking_number": "JJD149990121180203692",
      "carrier_slug": "dhlparcel-nl",
      "courier_name": "DHL Parcel NL",
      "status_tag": "Delivered",
      "title": "JJD149990121180203692",
      "order_id": "6001599847",
      "sales_office_id": "",
      "source": "csv_importer",
      "custom_fields": {},
      "last_checkpoint_id": "",
      "last_checkpoint_time": "2026-02-12T13:12:00+01:00",
      "last_checkpoint_location": "",
      "updated_at": "2026-02-16T00:43:13+00:00"
    },
    {
      "tracking_number": "JJD149990121180204774",
      "carrier_slug": "dhlparcel-nl",
      "courier_name": "DHL Parcel NL",
      "status_tag": "Delivered",
      "title": "JJD149990121180204774",
      "order_id": "6001608004",
      "sales_office_id": "",
      "source": "csv_importer",
      "custom_fields": {},
      "last_checkpoint_id": "",
      "last_checkpoint_time": "2026-02-12T13:12:00+01:00",
      "last_checkpoint_location": "",
      "updated_at": "2026-02-16T00:43:15+00:00"
    },
    {
      "tracking_number": "JJD149990121180203351",
      "carrier_slug": "dhlparcel-nl",
      "courier_name": "DHL Parcel NL",
      "status_tag": "Delivered",
      "title": "JJD149990121180203351",
      "order_id": "6001600237",
      "sales_office_id": "",
      "source": "csv_importer",
      "custom_fields": {},
      "last_checkpoint_id": "",
      "last_checkpoint_time": "2026-02-12T13:12:00+01:00",
      "last_checkpoint_location": "",
      "updated_at": "2026-02-16T00:43:13+00:00"
    },
    {
      "tracking_number": "JJD149990121180204497",
      "carrier_slug": "dhlparcel-nl",
      "courier_name": "DHL Parcel NL",
      "status_tag": "Delivered",
      "title": "JJD149990121180204497",
      "order_id": "6001598977",
      "sales_office_id": "",
      "source": "csv_importer",
      "custom_fields": {},
      "last_checkpoint_id": "",
      "last_checkpoint_time": "2026-02-12T13:12:00+01:00",
      "last_checkpoint_location": "",
      "updated_at": "2026-02-16T00:43:15+00:00"
    },
    {
      "tracking_number": "JJD149990121180203634",
      "carrier_slug": "dhlparcel-nl",
      "courier_name": "DHL Parcel NL",
      "status_tag": "Delivered",
      "title": "JJD149990121180203634",
      "order_id": "6001600133",
      "sales_office_id": "",
      "source": "csv_importer",
      "custom_fields": {},
      "last_checkpoint_id": "",
      "last_checkpoint_time": "2026-02-12T13:12:00+01:00",
      "last_checkpoint_location": "",
      "updated_at": "2026-02-16T00:43:14+00:00"
    },
    {
      "tracking_number": "JJD149990121180207187",
      "carrier_slug": "dhlparcel-nl",
      "courier_name": "DHL Parcel NL",
      "status_tag": "Delivered",
      "title": "JJD149990121180207187",
      "order_id": "6001613140",
      "sales_office_id": "",
      "source": "csv_importer",
      "custom_fields": {},
      "last_checkpoint_id": "",
      "last_checkpoint_time": "2026-02-13T10:25:00+01:00",
      "last_checkpoint_location": "",
      "updated_at": "2026-02-16T04:43:14+00:00"
    },
    {
      "tracking_number": "888454894430",
      "carrier_slug": "fedex",
      "courier_name": "FedEx®",
      "status_tag": "Delivered",
      "title": "888454894430",
      "order_id": "6001621241",
      "sales_office_id": "",
      "source": "csv_importer",
      "custom_fields": {},
      "last_checkpoint_id": "",
      "last_checkpoint_time": "2026-02-13T08:38:00+01:00",
      "last_checkpoint_location": "HEM-HARDINVAL, 80, 80600, FR, France",
      "updated_at": "2026-02-16T04:43:15+00:00"
    },
    {
      "tracking_number": "166050916805714",
      "carrier_slug": "brt-it-parcelid",
      "courier_name": "BRT Bartolini(Parcel ID)",
      "status_tag": "Delivered",
      "title": "166050916805714",
      "order_id": "6001617829",
      "sales_office_id": "",
      "source": "csv_importer",
      "custom_fields": {},
      "last_checkpoint_id": "",
      "last_checkpoint_time": "2026-02-10T12:00:00+01:00",
      "last_checkpoint_location": "MILANO SEDRIANO (050)",
      "updated_at": "2026-02-16T00:43:12+00:00"
    },
    {
      "tracking_number": "YVXA6MJ3",
      "carrier_slug": "gls",
      "courier_name": "GLS",
      "status_tag": "Delivered",
      "title": "YVXA6MJ3",
      "order_id": "6001617381",
      "sales_office_id": "",
      "source": "csv_importer",
      "custom_fields": {},
      "last_checkpoint_id": "",
      "last_checkpoint_time": "2026-01-14T14:00:00+01:00",
      "last_checkpoint_location": "DE, Germany",
      "updated_at": "2026-02-16T00:43:16+00:00"
    },
    {
      "tracking_number": "JJD149990121180207070",
      "carrier_slug": "dhlparcel-nl",
      "courier_name": "DHL Parcel NL",
      "status_tag": "Delivered",
      "title": "JJD149990121180207070",
      "order_id": "6001613343",
      "sales_office_id": "",
      "source": "csv_importer",
      "custom_fields": {},
      "last_checkpoint_id": "",
      "last_checkpoint_time": "2026-02-13T10:25:00+01:00",
      "last_checkpoint_location": "",
      "updated_at": "2026-02-16T04:43:12+00:00"
    },
    {
      "tracking_number": "75036117530530",
      "carrier_slug": "hermes-de",
      "courier_name": "Hermes Germany",
      "status_tag": "Delivered",
      "title": "75036117530530",
      "order_id": "6001617408",
      "sales_office_id": "",
      "source": "csv_importer",
      "custom_fields": {},
      "last_checkpoint_id": "",
      "last_checkpoint_time": "2026-02-12T11:15:51+01:00",
      "last_checkpoint_location": "Germany",
      "updated_at": "2026-02-16T00:43:16+00:00"
    },
    {
      "tracking_number": "75035117530175",
      "carrier_slug": "hermes-de",
      "courier_name": "Hermes Germany",
      "status_tag": "Delivered",
      "title": "75035117530175",
      "order_id": "6001617472",
      "sales_office_id": "",
      "source": "csv_importer",
      "custom_fields": {},
      "last_checkpoint_id": "",
      "last_checkpoint_time": "2026-02-11T11:46:01+01:00",
      "last_checkpoint_location": "Germany",
      "updated_at": "2026-02-16T00:43:13+00:00"
    },
    {
      "tracking_number": "MDP5K9Y6L6D",
      "carrier_slug": "dhlparcel-nl",
      "courier_name": "DHL Parcel NL",
      "status_tag": "Delivered",
      "title": "MDP5K9Y6L6D",
      "order_id": "6001620363",
      "sales_office_id": "",
      "source": "csv_importer",
      "custom_fields": {},
      "last_checkpoint_id": "",
      "last_checkpoint_time": "2026-02-02T13:09:42+01:00",
      "last_checkpoint_location": "",
      "updated_at": "2026-02-16T00:43:12+00:00"
    },
    {
      "tracking_number": "02040117000690",
      "carrier_slug": "hermes-de",
      "courier_name": "Hermes Germany",
      "status_tag": "Delivered",
      "title": "02040117000690",
      "order_id": "6001616229",
      "sales_office_id": "",
      "source": "csv_importer",
      "custom_fields": {},
      "last_checkpoint_id": "",
      "last_checkpoint_time": "2026-02-11T11:46:01+01:00",
      "last_checkpoint_location": "Germany",
      "updated_at": "2026-02-16T01:13:28+00:00"
    },
    {
      "tracking_number": "231257979948",
      "carrier_slug": "dhl-germany",
      "courier_name": "Deutsche Post DHL",
      "status_tag": "Delivered",
      "title": "231257979948",
      "order_id": "6001617473",
      "sales_office_id": "",
      "source": "csv_importer",
      "custom_fields": {},
      "last_checkpoint_id": "",
      "last_checkpoint_time": "2025-12-30T10:50:00+01:00",
      "last_checkpoint_location": "Germany",
      "updated_at": "2026-02-16T00:43:12+00:00"
    },
    {
      "tracking_number": "JJD149990121180207109",
      "carrier_slug": "dhlparcel-nl",
      "courier_name": "DHL Parcel NL",
      "status_tag": "Delivered",
      "title": "JJD149990121180207109",
      "order_id": "6001613328",
      "sales_office_id": "",
      "source": "csv_importer",
      "custom_fields": {},
      "last_checkpoint_id": "",
      "last_checkpoint_time": "2026-02-13T10:25:00+01:00",
      "last_checkpoint_location": "",
      "updated_at": "2026-02-16T04:43:12+00:00"
    },
    {
      "tracking_number": "JD014600012508815455",
      "carrier_slug": "dhl",
      "courier_name": "DHL Express",
      "status_tag": "Delivered",
      "title": "JD014600012508815455",
      "order_id": "6001620049",
      "sales_office_id": "",
      "source": "csv_importer",
      "custom_fields": {},
      "last_checkpoint_id": "",
      "last_checkpoint_time": "2026-02-09T14:17:15+01:00",
      "last_checkpoint_location": "EINDHOVEN-NLD, Netherlands",
      "updated_at": "2026-02-16T00:43:13+00:00"
    },
    {
      "tracking_number": "1ZR096K99088610321",
      "carrier_slug": "ups-api",
      "courier_name": "ups-api",
      "status_tag": "Delivered",
      "title": "1ZR096K99088610321",
      "order_id": "6001606033",
      "sales_office_id": "",
      "source": "csv_importer",
      "custom_fields": {
        "courier": "UPS",
        "custom_1": "returns_ups"
      },
      "last_checkpoint_id": "",
      "last_checkpoint_time": "2026-02-11T11:51:16-05:00",
      "last_checkpoint_location": "MOUNT POCONO, PA, 18344, US, United States",
      "updated_at": "2026-02-16T00:43:12+00:00"
    },
    {
      "tracking_number": "1ZR096K99088686278",
      "carrier_slug": "ups-api",
      "courier_name": "ups-api",
      "status_tag": "Delivered",
      "title": "1ZR096K99088686278",
      "order_id": "6001605983",
      "sales_office_id": "",
      "source": "csv_importer",
      "custom_fields": {
        "courier": "UPS",
        "custom_1": "returns_ups"
      },
      "last_checkpoint_id": "",
      "last_checkpoint_time": "2026-02-10T11:27:14-05:00",
      "last_checkpoint_location": "MOUNT POCONO, PA, 18344, US, United States",
      "updated_at": "2026-02-16T00:43:12+00:00"
    },
    {
      "tracking_number": "1ZR0960D9069205466",
      "carrier_slug": "ups-api",
      "courier_name": "ups-api",
      "status_tag": "Delivered",
      "title": "1ZR0960D9069205466",
      "order_id": "6001620030",
      "sales_office_id": "",
      "source": "csv_importer",
      "custom_fields": {
        "courier": "UPS",
        "custom_1": "returns_ups"
      },
      "last_checkpoint_id": "",
      "last_checkpoint_time": "2026-01-07T13:39:57-08:00",
      "last_checkpoint_location": "REDLANDS, CA, 92374, US, United States",
      "updated_at": "2026-02-16T00:43:12+00:00"
    },
    {
      "tracking_number": "08456093521115",
      "carrier_slug": "brt-it",
      "courier_name": "BRT Bartolini",
      "status_tag": "Delivered",
      "title": "08456093521115",
      "order_id": "6001617662",
      "sales_office_id": "",
      "source": "csv_importer",
      "custom_fields": {},
      "last_checkpoint_id": "",
      "last_checkpoint_time": "2026-02-10T12:00:00+01:00",
      "last_checkpoint_location": "MILANO SEDRIANO (050)",
      "updated_at": "2026-02-16T00:43:11+00:00"
    },
    {
      "tracking_number": "JD014600012508815454",
      "carrier_slug": "dhl",
      "courier_name": "DHL Express",
      "status_tag": "Delivered",
      "title": "JD014600012508815454",
      "order_id": "6001620049",
      "sales_office_id": "",
      "source": "csv_importer",
      "custom_fields": {},
      "last_checkpoint_id": "",
      "last_checkpoint_time": "2026-02-09T14:17:15+01:00",
      "last_checkpoint_location": "EINDHOVEN-NLD, Netherlands",
      "updated_at": "2026-02-16T00:43:12+00:00"
    },
    {
      "tracking_number": "66034117400114",
      "carrier_slug": "hermes-de",
      "courier_name": "Hermes Germany",
      "status_tag": "Delivered",
      "title": "66034117400114",
      "order_id": "6001616201",
      "sales_office_id": "",
      "source": "csv_importer",
      "custom_fields": {},
      "last_checkpoint_id": "",
      "last_checkpoint_time": "2026-02-09T11:12:30+01:00",
      "last_checkpoint_location": "Germany",
      "updated_at": "2026-02-16T00:43:12+00:00"
    },
    {
      "tracking_number": "YVXA6KXE",
      "carrier_slug": "gls",
      "courier_name": "GLS",
      "status_tag": "Delivered",
      "title": "YVXA6KXE",
      "order_id": "6001616935",
      "sales_office_id": "",
      "source": "csv_importer",
      "custom_fields": {},
      "last_checkpoint_id": "",
      "last_checkpoint_time": "2026-01-13T14:00:00+01:00",
      "last_checkpoint_location": "DE, Germany",
      "updated_at": "2026-02-16T00:43:16+00:00"
    },
    {
      "tracking_number": "08457093526976",
      "carrier_slug": "brt-it",
      "courier_name": "BRT Bartolini",
      "status_tag": "Delivered",
      "title": "08457093526976",
      "order_id": "6001617742",
      "sales_office_id": "",
      "source": "csv_importer",
      "custom_fields": {},
      "last_checkpoint_id": "",
      "last_checkpoint_time": "2026-02-12T12:00:00+01:00",
      "last_checkpoint_location": "MILANO SEDRIANO (050)",
      "updated_at": "2026-02-16T00:43:12+00:00"
    },
    {
      "tracking_number": "05222069711763",
      "carrier_slug": "dpd",
      "courier_name": "DPD",
      "status_tag": "Delivered",
      "title": "05222069711763",
      "order_id": "6001619069",
      "sales_office_id": "",
      "source": "csv_importer",
      "custom_fields": {},
      "last_checkpoint_id": "",
      "last_checkpoint_time": "2026-02-04T12:43:04+01:00",
      "last_checkpoint_location": "Etten-Leur, NL, Netherlands",
      "updated_at": "2026-02-16T00:43:15+00:00"
    },
    {
      "tracking_number": "REC000079421951",
      "carrier_slug": "spanish-seur-ftp",
      "courier_name": "spanish-seur-ftp",
      "status_tag": "Delivered",
      "title": "REC000079421951",
      "order_id": "6001604500",
      "sales_office_id": "",
      "source": "csv_importer",
      "custom_fields": {
        "courier": "spanish-seur-ftp",
        "custom_1": "Returns_spanish-seur"
      },
      "last_checkpoint_id": "",
      "last_checkpoint_time": "2026-02-13T18:58:00",
      "last_checkpoint_location": "",
      "updated_at": "2026-02-16T00:43:11+00:00"
    },
    {
      "tracking_number": "REC000079360278",
      "carrier_slug": "spanish-seur-ftp",
      "courier_name": "spanish-seur-ftp",
      "status_tag": "Delivered",
      "title": "REC000079360278",
      "order_id": "6001602745",
      "sales_office_id": "",
      "source": "csv_importer",
      "custom_fields": {
        "courier": "spanish-seur-ftp",
        "custom_1": "Returns_spanish-seur"
      },
      "last_checkpoint_id": "",
      "last_checkpoint_time": "2026-02-13T15:18:00",
      "last_checkpoint_location": "",
      "updated_at": "2026-02-16T00:43:10+00:00"
    },
    {
      "tracking_number": "502064370732",
      "carrier_slug": "sagawa",
      "courier_name": "Sagawa",
      "status_tag": "Delivered",
      "title": "502064370732",
      "order_id": "6001590096",
      "sales_office_id": "",
      "source": "csv_importer",
      "custom_fields": {
        "courier": "sagawa"
      },
      "last_checkpoint_id": "",
      "last_checkpoint_time": "2026-02-12T11:04:00+09:00",
      "last_checkpoint_location": "古河営業所, Japan",
      "updated_at": "2026-02-16T00:43:08+00:00"
    },
    {
      "tracking_number": "502064846253",
      "carrier_slug": "sagawa",
      "courier_name": "Sagawa",
      "status_tag": "Delivered",
      "title": "502064846253",
      "order_id": "6001600587",
      "sales_office_id": "",
      "source": "csv_importer",
      "custom_fields": {
        "courier": "sagawa"
      },
      "last_checkpoint_id": "",
      "last_checkpoint_time": "2026-02-13T11:20:00+09:00",
      "last_checkpoint_location": "古河営業所, Japan",
      "updated_at": "2026-02-16T00:43:08+00:00"
    },
    {
      "tracking_number": "502064507560",
      "carrier_slug": "sagawa",
      "courier_name": "Sagawa",
      "status_tag": "Delivered",
      "title": "502064507560",
      "order_id": "6001593589",
      "sales_office_id": "",
      "source": "csv_importer",
      "custom_fields": {
        "courier": "sagawa"
      },
      "last_checkpoint_id": "",
      "last_checkpoint_time": "2026-02-10T11:01:00+09:00",
      "last_checkpoint_location": "古河営業所, Japan",
      "updated_at": "2026-02-16T00:43:09+00:00"
    },
    {
      "tracking_number": "502064843195",
      "carrier_slug": "sagawa",
      "courier_name": "Sagawa",
      "status_tag": "Delivered",
      "title": "502064843195",
      "order_id": "6001600506",
      "sales_office_id": "",
      "source": "csv_importer",
      "custom_fields": {
        "courier": "sagawa"
      },
      "last_checkpoint_id": "",
      "last_checkpoint_time": "2026-02-16T10:49:00+09:00",
      "last_checkpoint_location": "古河営業所, Japan",
      "updated_at": "2026-02-16T02:13:09+00:00"
    },
    {
      "tracking_number": "ZDDO3J9S",
      "carrier_slug": "gls",
      "courier_name": "GLS",
      "status_tag": "Delivered",
      "title": "ZDDO3J9S",
      "order_id": "6001617583",
      "sales_office_id": "",
      "source": "csv_importer",
      "custom_fields": {
        "courier": "GLS",
        "custom_1": "returns_gls"
      },
      "last_checkpoint_id": "",
      "last_checkpoint_time": "2026-02-09T14:00:00+01:00",
      "last_checkpoint_location": "DE, Germany",
      "updated_at": "2026-02-16T00:42:55+00:00"
    },
    {
      "tracking_number": "ZDDO3JH8",
      "carrier_slug": "gls",
      "courier_name": "GLS",
      "status_tag": "Delivered",
      "title": "ZDDO3JH8",
      "order_id": "6001593269",
      "sales_office_id": "",
      "source": "csv_importer",
      "custom_fields": {
        "courier": "GLS",
        "custom_1": "returns_gls"
      },
      "last_checkpoint_id": "",
      "last_checkpoint_time": "2026-02-13T14:00:00+01:00",
      "last_checkpoint_location": "DE, Germany",
      "updated_at": "2026-02-16T00:42:55+00:00"
    },
    {
      "tracking_number": "ZDDO3JI3",
      "carrier_slug": "gls",
      "courier_name": "GLS",
      "status_tag": "Delivered",
      "title": "ZDDO3JI3",
      "order_id": "6001593515",
      "sales_office_id": "",
      "source": "csv_importer",
      "custom_fields": {
        "courier": "GLS",
        "custom_1": "returns_gls"
      },
      "last_checkpoint_id": "",
      "last_checkpoint_time": "2026-02-10T14:00:00+01:00",
      "last_checkpoint_location": "DE, Germany",
      "updated_at": "2026-02-16T00:42:55+00:00"
    },
    {
      "tracking_number": "05222006537575",
      "carrier_slug": "dpd",
      "courier_name": "DPD",
      "status_tag": "Delivered",
      "title": "05222006537575",
      "order_id": "6001619084",
      "sales_office_id": "",
      "source": "csv_importer",
      "custom_fields": {
        "courier": "dpd ",
        "custom_1": "returns_dpd"
      },
      "last_checkpoint_id": "",
      "last_checkpoint_time": "2026-02-13T18:50:34+01:00",
      "last_checkpoint_location": "Rijssen, NL, Netherlands",
      "updated_at": "2026-02-16T00:42:44+00:00"
    },
    {
      "tracking_number": "05222006537504",
      "carrier_slug": "dpd",
      "courier_name": "DPD",
      "status_tag": "Delivered",
      "title": "05222006537504",
      "order_id": "6001616336",
      "sales_office_id": "",
      "source": "csv_importer",
      "custom_fields": {
        "courier": "dpd ",
        "custom_1": "returns_dpd"
      },
      "last_checkpoint_id": "",
      "last_checkpoint_time": "2026-02-13T17:02:09+01:00",
      "last_checkpoint_location": "Vilvoorde, BE, Belgium",
      "updated_at": "2026-02-16T04:42:48+00:00"
    },
    {
      "tracking_number": "05222006537521",
      "carrier_slug": "dpd",
      "courier_name": "DPD",
      "status_tag": "Delivered",
      "title": "05222006537521",
      "order_id": "6001617679",
      "sales_office_id": "",
      "source": "csv_importer",
      "custom_fields": {
        "courier": "dpd ",
        "custom_1": "returns_dpd"
      },
      "last_checkpoint_id": "",
      "last_checkpoint_time": "2026-02-13T15:54:28+01:00",
      "last_checkpoint_location": "NL, Netherlands",
      "updated_at": "2026-02-16T00:42:44+00:00"
    },
    {
      "tracking_number": "05222006537550",
      "carrier_slug": "dpd",
      "courier_name": "DPD",
      "status_tag": "Delivered",
      "title": "05222006537550",
      "order_id": "6001618643",
      "sales_office_id": "",
      "source": "csv_importer",
      "custom_fields": {
        "courier": "dpd ",
        "custom_1": "returns_dpd"
      },
      "last_checkpoint_id": "",
      "last_checkpoint_time": "2026-02-13T15:41:22+01:00",
      "last_checkpoint_location": "Veenendaal, NL, Netherlands",
      "updated_at": "2026-02-16T00:42:45+00:00"
    },
    {
      "tracking_number": "05222006537508",
      "carrier_slug": "dpd",
      "courier_name": "DPD",
      "status_tag": "Delivered",
      "title": "05222006537508",
      "order_id": "6001616955",
      "sales_office_id": "",
      "source": "csv_importer",
      "custom_fields": {
        "courier": "dpd ",
        "custom_1": "returns_dpd"
      },
      "last_checkpoint_id": "",
      "last_checkpoint_time": "2026-02-14T09:46:04+01:00",
      "last_checkpoint_location": "Broendby, DK, Denmark",
      "updated_at": "2026-02-16T04:42:47+00:00"
    },
    {
      "tracking_number": "05222006537559",
      "carrier_slug": "dpd",
      "courier_name": "DPD",
      "status_tag": "Delivered",
      "title": "05222006537559",
      "order_id": "6001618983",
      "sales_office_id": "",
      "source": "csv_importer",
      "custom_fields": {
        "courier": "dpd ",
        "custom_1": "returns_dpd"
      },
      "last_checkpoint_id": "",
      "last_checkpoint_time": "2026-02-13T16:38:40+01:00",
      "last_checkpoint_location": "Berkel en Rodenrijs, NL, Netherlands",
      "updated_at": "2026-02-16T00:42:44+00:00"
    },
    {
      "tracking_number": "05222006537534",
      "carrier_slug": "dpd",
      "courier_name": "DPD",
      "status_tag": "Delivered",
      "title": "05222006537534",
      "order_id": "6001617993",
      "sales_office_id": "",
      "source": "csv_importer",
      "custom_fields": {
        "courier": "dpd ",
        "custom_1": "returns_dpd"
      },
      "last_checkpoint_id": "",
      "last_checkpoint_time": "2026-02-14T10:07:21+01:00",
      "last_checkpoint_location": "Meppel, NL, Netherlands",
      "updated_at": "2026-02-16T00:42:44+00:00"
    },
    {
      "tracking_number": "05222006537560",
      "carrier_slug": "dpd",
      "courier_name": "DPD",
      "status_tag": "Delivered",
      "title": "05222006537560",
      "order_id": "6001618983",
      "sales_office_id": "",
      "source": "csv_importer",
      "custom_fields": {
        "courier": "dpd ",
        "custom_1": "returns_dpd"
      },
      "last_checkpoint_id": "",
      "last_checkpoint_time": "2026-02-13T16:38:40+01:00",
      "last_checkpoint_location": "Berkel en Rodenrijs, NL, Netherlands",
      "updated_at": "2026-02-16T00:42:44+00:00"
    },
    {
      "tracking_number": "05222006537558",
      "carrier_slug": "dpd",
      "courier_name": "DPD",
      "status_tag": "Delivered",
      "title": "05222006537558",
      "order_id": "6001618983",
      "sales_office_id": "",
      "source": "csv_importer",
      "custom_fields": {
        "courier": "dpd ",
        "custom_1": "returns_dpd"
      },
      "last_checkpoint_id": "",
      "last_checkpoint_time": "2026-02-13T16:38:40+01:00",
      "last_checkpoint_location": "Berkel en Rodenrijs, NL, Netherlands",
      "updated_at": "2026-02-16T00:42:43+00:00"
    },
    {
      "tracking_number": "05222006537568",
      "carrier_slug": "dpd",
      "courier_name": "DPD",
      "status_tag": "Delivered",
      "title": "05222006537568",
      "order_id": "6001619037",
      "sales_office_id": "",
      "source": "csv_importer",
      "custom_fields": {
        "courier": "dpd ",
        "custom_1": "returns_dpd"
      },
      "last_checkpoint_id": "",
      "last_checkpoint_time": "2026-02-14T11:37:24+01:00",
      "last_checkpoint_location": "Meppel, NL, Netherlands",
      "updated_at": "2026-02-16T00:42:43+00:00"
    },
    {
      "tracking_number": "05222006537530",
      "carrier_slug": "dpd",
      "courier_name": "DPD",
      "status_tag": "Delivered",
      "title": "05222006537530",
      "order_id": "6001617928",
      "sales_office_id": "",
      "source": "csv_importer",
      "custom_fields": {
        "courier": "dpd ",
        "custom_1": "returns_dpd"
      },
      "last_checkpoint_id": "",
      "last_checkpoint_time": "2026-02-13T16:00:56+01:00",
      "last_checkpoint_location": "Kortrijk, BE, Belgium",
      "updated_at": "2026-02-16T04:42:44+00:00"
    },
    {
      "tracking_number": "05222006537547",
      "carrier_slug": "dpd",
      "courier_name": "DPD",
      "status_tag": "Delivered",
      "title": "05222006537547",
      "order_id": "6001618557",
      "sales_office_id": "",
      "source": "csv_importer",
      "custom_fields": {
        "courier": "dpd ",
        "custom_1": "returns_dpd"
      },
      "last_checkpoint_id": "",
      "last_checkpoint_time": "2026-02-14T13:35:19+01:00",
      "last_checkpoint_location": "Vijfhuizen, NL, Netherlands",
      "updated_at": "2026-02-16T00:42:42+00:00"
    },
    {
      "tracking_number": "05222006537546",
      "carrier_slug": "dpd",
      "courier_name": "DPD",
      "status_tag": "Delivered",
      "title": "05222006537546",
      "order_id": "6001618519",
      "sales_office_id": "",
      "source": "csv_importer",
      "custom_fields": {
        "courier": "dpd ",
        "custom_1": "returns_dpd"
      },
      "last_checkpoint_id": "",
      "last_checkpoint_time": "2026-02-14T11:21:48+01:00",
      "last_checkpoint_location": "Veenendaal, NL, Netherlands",
      "updated_at": "2026-02-16T00:42:43+00:00"
    },
    {
      "tracking_number": "05222006537561",
      "carrier_slug": "dpd",
      "courier_name": "DPD",
      "status_tag": "Delivered",
      "title": "05222006537561",
      "order_id": "6001618983",
      "sales_office_id": "",
      "source": "csv_importer",
      "custom_fields": {
        "courier": "dpd ",
        "custom_1": "returns_dpd"
      },
      "last_checkpoint_id": "",
      "last_checkpoint_time": "2026-02-13T16:38:40+01:00",
      "last_checkpoint_location": "Berkel en Rodenrijs, NL, Netherlands",
      "updated_at": "2026-02-16T00:42:42+00:00"
    },
    {
      "tracking_number": "05228742801542",
      "carrier_slug": "dpd",
      "courier_name": "DPD",
      "status_tag": "Delivered",
      "title": "05228742801542",
      "order_id": "6001621273",
      "sales_office_id": "",
      "source": "csv_importer",
      "custom_fields": {
        "courier": "dpd ",
        "custom_1": "returns_dpd"
      },
      "last_checkpoint_id": "",
      "last_checkpoint_time": "2026-02-14T10:30:52+01:00",
      "last_checkpoint_location": "Meppel, NL, Netherlands",
      "updated_at": "2026-02-16T00:42:41+00:00"
    },
    {
      "tracking_number": "05222006534798",
      "carrier_slug": "dpd",
      "courier_name": "DPD",
      "status_tag": "Delivered",
      "title": "05222006534798",
      "order_id": "6001618978",
      "sales_office_id": "",
      "source": "csv_importer",
      "custom_fields": {
        "courier": "dpd ",
        "custom_1": "returns_dpd"
      },
      "last_checkpoint_id": "",
      "last_checkpoint_time": "2026-01-14T09:14:23+01:00",
      "last_checkpoint_location": "Oirschot (NL), Netherlands",
      "updated_at": "2026-02-16T00:42:43+00:00"
    },
    {
      "tracking_number": "0053023894536W",
      "carrier_slug": "dpd",
      "courier_name": "DPD",
      "status_tag": "Delivered",
      "title": "0053023894536W",
      "order_id": "6001593221",
      "sales_office_id": "",
      "source": "csv_importer",
      "custom_fields": {
        "courier": "dpd ",
        "custom_1": "returns_dpd"
      },
      "last_checkpoint_id": "",
      "last_checkpoint_time": "2026-02-10T09:32:00+01:00",
      "last_checkpoint_location": "ROSANOW, PL, Poland",
      "updated_at": "2026-02-16T00:42:39+00:00"
    },
    {
      "tracking_number": "0053033146227W",
      "carrier_slug": "dpd",
      "courier_name": "DPD",
      "status_tag": "Delivered",
      "title": "0053033146227W",
      "order_id": "6001595819",
      "sales_office_id": "",
      "source": "csv_importer",
      "custom_fields": {
        "courier": "dpd ",
        "custom_1": "returns_dpd"
      },
      "last_checkpoint_id": "",
      "last_checkpoint_time": "2026-02-11T12:40:32+01:00",
      "last_checkpoint_location": "ROSANOW, PL, Poland",
      "updated_at": "2026-02-16T00:42:39+00:00"
    },
    {
      "tracking_number": "0053033443836W",
      "carrier_slug": "dpd",
      "courier_name": "DPD",
      "status_tag": "Delivered",
      "title": "0053033443836W",
      "order_id": "6001596265",
      "sales_office_id": "",
      "source": "csv_importer",
      "custom_fields": {
        "courier": "dpd ",
        "custom_1": "returns_dpd"
      },
      "last_checkpoint_id": "",
      "last_checkpoint_time": "2026-02-10T10:20:53+01:00",
      "last_checkpoint_location": "Warszawa, PL, Poland",
      "updated_at": "2026-02-16T00:42:40+00:00"
    },
    {
      "tracking_number": "0053027296931W",
      "carrier_slug": "dpd",
      "courier_name": "DPD",
      "status_tag": "Delivered",
      "title": "0053027296931W",
      "order_id": "6001602509",
      "sales_office_id": "",
      "source": "csv_importer",
      "custom_fields": {
        "courier": "dpd ",
        "custom_1": "returns_dpd"
      },
      "last_checkpoint_id": "",
      "last_checkpoint_time": "2026-02-11T15:11:11+01:00",
      "last_checkpoint_location": "Rzekun, PL, Poland",
      "updated_at": "2026-02-16T00:42:41+00:00"
    },
    {
      "tracking_number": "0053030868401W",
      "carrier_slug": "dpd",
      "courier_name": "DPD",
      "status_tag": "Delivered",
      "title": "0053030868401W",
      "order_id": "6001595149",
      "sales_office_id": "",
      "source": "csv_importer",
      "custom_fields": {
        "courier": "dpd ",
        "custom_1": "returns_dpd"
      },
      "last_checkpoint_id": "",
      "last_checkpoint_time": "2026-02-10T09:32:00+01:00",
      "last_checkpoint_location": "ROSANOW, PL, Poland",
      "updated_at": "2026-02-16T00:42:38+00:00"
    },
    {
      "tracking_number": "0053031953430W",
      "carrier_slug": "dpd",
      "courier_name": "DPD",
      "status_tag": "Delivered",
      "title": "0053031953430W",
      "order_id": "6001595296",
      "sales_office_id": "",
      "source": "csv_importer",
      "custom_fields": {
        "courier": "dpd ",
        "custom_1": "returns_dpd"
      },
      "last_checkpoint_id": "",
      "last_checkpoint_time": "2026-02-10T09:32:00+01:00",
      "last_checkpoint_location": "ROSANOW, PL, Poland",
      "updated_at": "2026-02-16T00:42:40+00:00"
    },
    {
      "tracking_number": "0053031468295W",
      "carrier_slug": "dpd",
      "courier_name": "DPD",
      "status_tag": "Delivered",
      "title": "0053031468295W",
      "order_id": "6001595192",
      "sales_office_id": "",
      "source": "csv_importer",
      "custom_fields": {
        "courier": "dpd ",
        "custom_1": "returns_dpd"
      },
      "last_checkpoint_id": "",
      "last_checkpoint_time": "2026-02-13T07:35:00+01:00",
      "last_checkpoint_location": "ROSANOW, PL, Poland",
      "updated_at": "2026-02-16T04:42:42+00:00"
    },
    {
      "tracking_number": "0053031958853W",
      "carrier_slug": "dpd",
      "courier_name": "DPD",
      "status_tag": "Delivered",
      "title": "0053031958853W",
      "order_id": "6001595282",
      "sales_office_id": "",
      "source": "csv_importer",
      "custom_fields": {
        "courier": "dpd ",
        "custom_1": "returns_dpd"
      },
      "last_checkpoint_id": "",
      "last_checkpoint_time": "2026-02-10T09:32:00+01:00",
      "last_checkpoint_location": "ROSANOW, PL, Poland",
      "updated_at": "2026-02-16T00:42:39+00:00"
    },
    {
      "tracking_number": "0053033076671W",
      "carrier_slug": "dpd",
      "courier_name": "DPD",
      "status_tag": "Delivered",
      "title": "0053033076671W",
      "order_id": "6001595790",
      "sales_office_id": "",
      "source": "csv_importer",
      "custom_fields": {
        "courier": "dpd ",
        "custom_1": "returns_dpd"
      },
      "last_checkpoint_id": "",
      "last_checkpoint_time": "2026-02-10T09:32:00+01:00",
      "last_checkpoint_location": "ROSANOW, PL, Poland",
      "updated_at": "2026-02-16T00:42:40+00:00"
    },
    {
      "tracking_number": "0053030152764W",
      "carrier_slug": "dpd",
      "courier_name": "DPD",
      "status_tag": "Delivered",
      "title": "0053030152764W",
      "order_id": "6001595027",
      "sales_office_id": "",
      "source": "csv_importer",
      "custom_fields": {
        "courier": "dpd ",
        "custom_1": "returns_dpd"
      },
      "last_checkpoint_id": "",
      "last_checkpoint_time": "2026-02-11T09:00:00+01:00",
      "last_checkpoint_location": "ROSANOW, PL, Poland",
      "updated_at": "2026-02-16T00:42:39+00:00"
    },
    {
      "tracking_number": "0053030626730W",
      "carrier_slug": "dpd",
      "courier_name": "DPD",
      "status_tag": "Delivered",
      "title": "0053030626730W",
      "order_id": "6001595092",
      "sales_office_id": "",
      "source": "csv_importer",
      "custom_fields": {
        "courier": "dpd ",
        "custom_1": "returns_dpd"
      },
      "last_checkpoint_id": "",
      "last_checkpoint_time": "2026-02-10T09:32:00+01:00",
      "last_checkpoint_location": "ROSANOW, PL, Poland",
      "updated_at": "2026-02-16T00:42:40+00:00"
    },
    {
      "tracking_number": "0053024547723W",
      "carrier_slug": "dpd",
      "courier_name": "DPD",
      "status_tag": "Delivered",
      "title": "0053024547723W",
      "order_id": "6001593697",
      "sales_office_id": "",
      "source": "csv_importer",
      "custom_fields": {
        "courier": "dpd ",
        "custom_1": "returns_dpd"
      },
      "last_checkpoint_id": "",
      "last_checkpoint_time": "2026-02-12T08:00:00+01:00",
      "last_checkpoint_location": "ROSANOW, PL, Poland",
      "updated_at": "2026-02-16T00:42:39+00:00"
    },
    {
      "tracking_number": "05222006537335",
      "carrier_slug": "dpd",
      "courier_name": "DPD",
      "status_tag": "Delivered",
      "title": "05222006537335",
      "order_id": "6001610826",
      "sales_office_id": "",
      "source": "csv_importer",
      "custom_fields": {
        "courier": "dpd ",
        "custom_1": "returns_dpd"
      },
      "last_checkpoint_id": "",
      "last_checkpoint_time": "2026-02-13T10:55:13+01:00",
      "last_checkpoint_location": "Oirschot, NL, Netherlands",
      "updated_at": "2026-02-16T00:42:39+00:00"
    },
    {
      "tracking_number": "0053026264951W",
      "carrier_slug": "dpd",
      "courier_name": "DPD",
      "status_tag": "Delivered",
      "title": "0053026264951W",
      "order_id": "6001609072",
      "sales_office_id": "",
      "source": "csv_importer",
      "custom_fields": {
        "courier": "dpd ",
        "custom_1": "returns_dpd"
      },
      "last_checkpoint_id": "",
      "last_checkpoint_time": "2026-02-13T07:35:00+01:00",
      "last_checkpoint_location": "ROSANOW, PL, Poland",
      "updated_at": "2026-02-16T05:12:45+00:00"
    },
    {
      "tracking_number": "0053030152876W",
      "carrier_slug": "dpd",
      "courier_name": "DPD",
      "status_tag": "Delivered",
      "title": "0053030152876W",
      "order_id": "6001595027",
      "sales_office_id": "",
      "source": "csv_importer",
      "custom_fields": {
        "courier": "dpd ",
        "custom_1": "returns_dpd"
      },
      "last_checkpoint_id": "",
      "last_checkpoint_time": "2026-02-11T09:00:00+01:00",
      "last_checkpoint_location": "ROSANOW, PL, Poland",
      "updated_at": "2026-02-16T00:42:39+00:00"
    },
    {
      "tracking_number": "0053023896089W",
      "carrier_slug": "dpd",
      "courier_name": "DPD",
      "status_tag": "Delivered",
      "title": "0053023896089W",
      "order_id": "6001593231",
      "sales_office_id": "",
      "source": "csv_importer",
      "custom_fields": {
        "courier": "dpd ",
        "custom_1": "returns_dpd"
      },
      "last_checkpoint_id": "",
      "last_checkpoint_time": "2026-02-10T12:33:27+01:00",
      "last_checkpoint_location": "Lublin, PL, Poland",
      "updated_at": "2026-02-16T00:42:39+00:00"
    },
    {
      "tracking_number": "0053032586662W",
      "carrier_slug": "dpd",
      "courier_name": "DPD",
      "status_tag": "Delivered",
      "title": "0053032586662W",
      "order_id": "6001595473",
      "sales_office_id": "",
      "source": "csv_importer",
      "custom_fields": {
        "courier": "dpd ",
        "custom_1": "returns_dpd"
      },
      "last_checkpoint_id": "",
      "last_checkpoint_time": "2026-02-09T11:00:00+01:00",
      "last_checkpoint_location": "ROSANOW, PL, Poland",
      "updated_at": "2026-02-16T00:42:48+00:00"
    },
    {
      "tracking_number": "0053034831890W",
      "carrier_slug": "dpd",
      "courier_name": "DPD",
      "status_tag": "Delivered",
      "title": "0053034831890W",
      "order_id": "6001600279",
      "sales_office_id": "",
      "source": "csv_importer",
      "custom_fields": {
        "courier": "dpd ",
        "custom_1": "returns_dpd"
      },
      "last_checkpoint_id": "",
      "last_checkpoint_time": "2026-02-12T08:00:00+01:00",
      "last_checkpoint_location": "ROSANOW, PL, Poland",
      "updated_at": "2026-02-16T00:42:39+00:00"
    },
    {
      "tracking_number": "0053034719034W",
      "carrier_slug": "dpd",
      "courier_name": "DPD",
      "status_tag": "Delivered",
      "title": "0053034719034W",
      "order_id": "6001600013",
      "sales_office_id": "",
      "source": "csv_importer",
      "custom_fields": {
        "courier": "dpd ",
        "custom_1": "returns_dpd"
      },
      "last_checkpoint_id": "",
      "last_checkpoint_time": "2026-02-11T13:46:59+01:00",
      "last_checkpoint_location": "Glogow Malopolski, PL, Poland",
      "updated_at": "2026-02-16T00:42:40+00:00"
    },
    {
      "tracking_number": "0053034173781W",
      "carrier_slug": "dpd",
      "courier_name": "DPD",
      "status_tag": "Delivered",
      "title": "0053034173781W",
      "order_id": "6001597868",
      "sales_office_id": "",
      "source": "csv_importer",
      "custom_fields": {
        "courier": "dpd ",
        "custom_1": "returns_dpd"
      },
      "last_checkpoint_id": "",
      "last_checkpoint_time": "2026-02-10T17:21:24+01:00",
      "last_checkpoint_location": "Zerniki, PL, Poland",
      "updated_at": "2026-02-16T00:42:39+00:00"
    },
    {
      "tracking_number": "0053034163545W",
      "carrier_slug": "dpd",
      "courier_name": "DPD",
      "status_tag": "Delivered",
      "title": "0053034163545W",
      "order_id": "6001597101",
      "sales_office_id": "",
      "source": "csv_importer",
      "custom_fields": {
        "courier": "dpd ",
        "custom_1": "returns_dpd"
      },
      "last_checkpoint_id": "",
      "last_checkpoint_time": "2026-02-09T14:25:25+01:00",
      "last_checkpoint_location": "Zerniki, PL, Poland",
      "updated_at": "2026-02-16T00:42:40+00:00"
    },
    {
      "tracking_number": "0053034717879W",
      "carrier_slug": "dpd",
      "courier_name": "DPD",
      "status_tag": "Delivered",
      "title": "0053034717879W",
      "order_id": "6001599923",
      "sales_office_id": "",
      "source": "csv_importer",
      "custom_fields": {
        "courier": "dpd ",
        "custom_1": "returns_dpd"
      },
      "last_checkpoint_id": "",
      "last_checkpoint_time": "2026-02-10T13:51:40+01:00",
      "last_checkpoint_location": "Wloclawek, PL, Poland",
      "updated_at": "2026-02-16T00:42:39+00:00"
    },
    {
      "tracking_number": "0053034163637W",
      "carrier_slug": "dpd",
      "courier_name": "DPD",
      "status_tag": "Delivered",
      "title": "0053034163637W",
      "order_id": "6001597101",
      "sales_office_id": "",
      "source": "csv_importer",
      "custom_fields": {
        "courier": "dpd ",
        "custom_1": "returns_dpd"
      },
      "last_checkpoint_id": "",
      "last_checkpoint_time": "2026-02-09T14:25:25+01:00",
      "last_checkpoint_location": "Zerniki, PL, Poland",
      "updated_at": "2026-02-16T00:42:38+00:00"
    },
    {
      "tracking_number": "0053034700689W",
      "carrier_slug": "dpd",
      "courier_name": "DPD",
      "status_tag": "Delivered",
      "title": "0053034700689W",
      "order_id": "6001599280",
      "sales_office_id": "",
      "source": "csv_importer",
      "custom_fields": {
        "courier": "dpd ",
        "custom_1": "returns_dpd"
      },
      "last_checkpoint_id": "",
      "last_checkpoint_time": "2026-02-12T15:51:26+01:00",
      "last_checkpoint_location": "Warszawa, PL, Poland",
      "updated_at": "2026-02-16T00:42:40+00:00"
    },
    {
      "tracking_number": "0053034173249W",
      "carrier_slug": "dpd",
      "courier_name": "DPD",
      "status_tag": "Delivered",
      "title": "0053034173249W",
      "order_id": "6001597781",
      "sales_office_id": "",
      "source": "csv_importer",
      "custom_fields": {
        "courier": "dpd ",
        "custom_1": "returns_dpd"
      },
      "last_checkpoint_id": "",
      "last_checkpoint_time": "2026-02-12T11:01:41+01:00",
      "last_checkpoint_location": "Piotrkow Trybunalski, PL, Poland",
      "updated_at": "2026-02-16T00:42:40+00:00"
    },
    {
      "tracking_number": "0053034170940W",
      "carrier_slug": "dpd",
      "courier_name": "DPD",
      "status_tag": "Delivered",
      "title": "0053034170940W",
      "order_id": "6001597475",
      "sales_office_id": "",
      "source": "csv_importer",
      "custom_fields": {
        "courier": "dpd ",
        "custom_1": "returns_dpd"
      },
      "last_checkpoint_id": "",
      "last_checkpoint_time": "2026-02-10T12:04:05+01:00",
      "last_checkpoint_location": "Czechowice-Dziedzice, PL, Poland",
      "updated_at": "2026-02-16T00:42:39+00:00"
    },
    {
      "tracking_number": "0053034169726W",
      "carrier_slug": "dpd",
      "courier_name": "DPD",
      "status_tag": "Delivered",
      "title": "0053034169726W",
      "order_id": "6001597357",
      "sales_office_id": "",
      "source": "csv_importer",
      "custom_fields": {
        "courier": "dpd ",
        "custom_1": "returns_dpd"
      },
      "last_checkpoint_id": "",
      "last_checkpoint_time": "2026-02-11T09:00:00+01:00",
      "last_checkpoint_location": "ROSANOW, PL, Poland",
      "updated_at": "2026-02-16T00:42:44+00:00"
    },
    {
      "tracking_number": "0053043090076W",
      "carrier_slug": "dpd",
      "courier_name": "DPD",
      "status_tag": "Delivered",
      "title": "0053043090076W",
      "order_id": "6001602305",
      "sales_office_id": "",
      "source": "csv_importer",
      "custom_fields": {
        "courier": "dpd ",
        "custom_1": "returns_dpd"
      },
      "last_checkpoint_id": "",
      "last_checkpoint_time": "2026-02-11T13:53:12+01:00",
      "last_checkpoint_location": "Zerniki, PL, Poland",
      "updated_at": "2026-02-16T00:42:39+00:00"
    },
    {
      "tracking_number": "0053038719847W",
      "carrier_slug": "dpd",
      "courier_name": "DPD",
      "status_tag": "Delivered",
      "title": "0053038719847W",
      "order_id": "6001601675",
      "sales_office_id": "",
      "source": "csv_importer",
      "custom_fields": {
        "courier": "dpd ",
        "custom_1": "returns_dpd"
      },
      "last_checkpoint_id": "",
      "last_checkpoint_time": "2026-02-10T09:32:00+01:00",
      "last_checkpoint_location": "ROSANOW, PL, Poland",
      "updated_at": "2026-02-16T00:42:39+00:00"
    },
    {
      "tracking_number": "0053041252981W",
      "carrier_slug": "dpd",
      "courier_name": "DPD",
      "status_tag": "Delivered",
      "title": "0053041252981W",
      "order_id": "6001602136",
      "sales_office_id": "",
      "source": "csv_importer",
      "custom_fields": {
        "courier": "dpd ",
        "custom_1": "returns_dpd"
      },
      "last_checkpoint_id": "",
      "last_checkpoint_time": "2026-02-12T08:00:00+01:00",
      "last_checkpoint_location": "ROSANOW, PL, Poland",
      "updated_at": "2026-02-16T00:42:40+00:00"
    },
    {
      "tracking_number": "0053046469134W",
      "carrier_slug": "dpd",
      "courier_name": "DPD",
      "status_tag": "Delivered",
      "title": "0053046469134W",
      "order_id": "6001602961",
      "sales_office_id": "",
      "source": "csv_importer",
      "custom_fields": {
        "courier": "dpd ",
        "custom_1": "returns_dpd"
      },
      "last_checkpoint_id": "",
      "last_checkpoint_time": "2026-02-12T08:00:00+01:00",
      "last_checkpoint_location": "ROSANOW, PL, Poland",
      "updated_at": "2026-02-16T00:42:38+00:00"
    },
    {
      "tracking_number": "0053043696019W",
      "carrier_slug": "dpd",
      "courier_name": "DPD",
      "status_tag": "Delivered",
      "title": "0053043696019W",
      "order_id": "6001602360",
      "sales_office_id": "",
      "source": "csv_importer",
      "custom_fields": {
        "courier": "dpd ",
        "custom_1": "returns_dpd"
      },
      "last_checkpoint_id": "",
      "last_checkpoint_time": "2026-02-10T12:46:33+01:00",
      "last_checkpoint_location": "Bialystok, PL, Poland",
      "updated_at": "2026-02-16T00:42:40+00:00"
    },
    {
      "tracking_number": "0053038324535W",
      "carrier_slug": "dpd",
      "courier_name": "DPD",
      "status_tag": "Delivered",
      "title": "0053038324535W",
      "order_id": "6001601571",
      "sales_office_id": "",
      "source": "csv_importer",
      "custom_fields": {
        "courier": "dpd ",
        "custom_1": "returns_dpd"
      },
      "last_checkpoint_id": "",
      "last_checkpoint_time": "2026-02-12T08:00:00+01:00",
      "last_checkpoint_location": "ROSANOW, PL, Poland",
      "updated_at": "2026-02-16T00:42:39+00:00"
    },
    {
      "tracking_number": "0053038324655W",
      "carrier_slug": "dpd",
      "courier_name": "DPD",
      "status_tag": "Delivered",
      "title": "0053038324655W",
      "order_id": "6001601571",
      "sales_office_id": "",
      "source": "csv_importer",
      "custom_fields": {
        "courier": "dpd ",
        "custom_1": "returns_dpd"
      },
      "last_checkpoint_id": "",
      "last_checkpoint_time": "2026-02-12T08:00:00+01:00",
      "last_checkpoint_location": "ROSANOW, PL, Poland",
      "updated_at": "2026-02-16T00:42:38+00:00"
    },
    {
      "tracking_number": "0053041253016W",
      "carrier_slug": "dpd",
      "courier_name": "DPD",
      "status_tag": "Delivered",
      "title": "0053041253016W",
      "order_id": "6001602136",
      "sales_office_id": "",
      "source": "csv_importer",
      "custom_fields": {
        "courier": "dpd ",
        "custom_1": "returns_dpd"
      },
      "last_checkpoint_id": "",
      "last_checkpoint_time": "2026-02-13T17:45:00+01:00",
      "last_checkpoint_location": "ROSANOW, PL, Poland",
      "updated_at": "2026-02-16T04:42:42+00:00"
    },
    {
      "tracking_number": "0053042398046W",
      "carrier_slug": "dpd",
      "courier_name": "DPD",
      "status_tag": "Delivered",
      "title": "0053042398046W",
      "order_id": "6001602236",
      "sales_office_id": "",
      "source": "csv_importer",
      "custom_fields": {
        "courier": "dpd ",
        "custom_1": "returns_dpd"
      },
      "last_checkpoint_id": "",
      "last_checkpoint_time": "2026-02-13T07:35:00+01:00",
      "last_checkpoint_location": "ROSANOW, PL, Poland",
      "updated_at": "2026-02-16T04:42:42+00:00"
    },
    {
      "tracking_number": "0053050465335W",
      "carrier_slug": "dpd",
      "courier_name": "DPD",
      "status_tag": "Delivered",
      "title": "0053050465335W",
      "order_id": "6001605968",
      "sales_office_id": "",
      "source": "csv_importer",
      "custom_fields": {
        "courier": "dpd ",
        "custom_1": "returns_dpd"
      },
      "last_checkpoint_id": "",
      "last_checkpoint_time": "2026-02-12T08:00:00+01:00",
      "last_checkpoint_location": "ROSANOW, PL, Poland",
      "updated_at": "2026-02-16T00:42:43+00:00"
    },
    {
      "tracking_number": "0053038324351W",
      "carrier_slug": "dpd",
      "courier_name": "DPD",
      "status_tag": "Delivered",
      "title": "0053038324351W",
      "order_id": "6001601571",
      "sales_office_id": "",
      "source": "csv_importer",
      "custom_fields": {
        "courier": "dpd ",
        "custom_1": "returns_dpd"
      },
      "last_checkpoint_id": "",
      "last_checkpoint_time": "2026-02-12T08:00:00+01:00",
      "last_checkpoint_location": "ROSANOW, PL, Poland",
      "updated_at": "2026-02-16T00:42:39+00:00"
    },
    {
      "tracking_number": "0053048029835W",
      "carrier_slug": "dpd",
      "courier_name": "DPD",
      "status_tag": "Delivered",
      "title": "0053048029835W",
      "order_id": "6001604891",
      "sales_office_id": "",
      "source": "csv_importer",
      "custom_fields": {
        "courier": "dpd ",
        "custom_1": "returns_dpd"
      },
      "last_checkpoint_id": "",
      "last_checkpoint_time": "2026-02-11T09:00:00+01:00",
      "last_checkpoint_location": "ROSANOW, PL, Poland",
      "updated_at": "2026-02-16T00:42:37+00:00"
    },
    {
      "tracking_number": "0053047922247W",
      "carrier_slug": "dpd",
      "courier_name": "DPD",
      "status_tag": "Delivered",
      "title": "0053047922247W",
      "order_id": "6001603744",
      "sales_office_id": "",
      "source": "csv_importer",
      "custom_fields": {
        "courier": "dpd ",
        "custom_1": "returns_dpd"
      },
      "last_checkpoint_id": "",
      "last_checkpoint_time": "2026-02-12T08:00:00+01:00",
      "last_checkpoint_location": "ROSANOW, PL, Poland",
      "updated_at": "2026-02-16T00:42:38+00:00"
    },
    {
      "tracking_number": "0053047946189W",
      "carrier_slug": "dpd",
      "courier_name": "DPD",
      "status_tag": "Delivered",
      "title": "0053047946189W",
      "order_id": "6001604780",
      "sales_office_id": "",
      "source": "csv_importer",
      "custom_fields": {
        "courier": "dpd ",
        "custom_1": "returns_dpd"
      },
      "last_checkpoint_id": "",
      "last_checkpoint_time": "2026-02-12T08:00:00+01:00",
      "last_checkpoint_location": "ROSANOW, PL, Poland",
      "updated_at": "2026-02-16T00:42:58+00:00"
    },
    {
      "tracking_number": "0053044440941W",
      "carrier_slug": "dpd",
      "courier_name": "DPD",
      "status_tag": "Delivered",
      "title": "0053044440941W",
      "order_id": "6001602466",
      "sales_office_id": "",
      "source": "csv_importer",
      "custom_fields": {
        "courier": "dpd ",
        "custom_1": "returns_dpd"
      },
      "last_checkpoint_id": "",
      "last_checkpoint_time": "2026-02-12T08:00:00+01:00",
      "last_checkpoint_location": "ROSANOW, PL, Poland",
      "updated_at": "2026-02-16T00:42:38+00:00"
    },
    {
      "tracking_number": "0053046469011W",
      "carrier_slug": "dpd",
      "courier_name": "DPD",
      "status_tag": "Delivered",
      "title": "0053046469011W",
      "order_id": "6001602961",
      "sales_office_id": "",
      "source": "csv_importer",
      "custom_fields": {
        "courier": "dpd ",
        "custom_1": "returns_dpd"
      },
      "last_checkpoint_id": "",
      "last_checkpoint_time": "2026-02-12T08:00:00+01:00",
      "last_checkpoint_location": "ROSANOW, PL, Poland",
      "updated_at": "2026-02-16T00:42:44+00:00"
    },
    {
      "tracking_number": "0053048004190W",
      "carrier_slug": "dpd",
      "courier_name": "DPD",
      "status_tag": "Delivered",
      "title": "0053048004190W",
      "order_id": "6001604851",
      "sales_office_id": "",
      "source": "csv_importer",
      "custom_fields": {
        "courier": "dpd ",
        "custom_1": "returns_dpd"
      },
      "last_checkpoint_id": "",
      "last_checkpoint_time": "2026-02-10T16:44:37+01:00",
      "last_checkpoint_location": "Lisia Gora, PL, Poland",
      "updated_at": "2026-02-16T00:42:57+00:00"
    },
    {
      "tracking_number": "0053050095966W",
      "carrier_slug": "dpd",
      "courier_name": "DPD",
      "status_tag": "Delivered",
      "title": "0053050095966W",
      "order_id": "6001605981",
      "sales_office_id": "",
      "source": "csv_importer",
      "custom_fields": {
        "courier": "dpd ",
        "custom_1": "returns_dpd"
      },
      "last_checkpoint_id": "",
      "last_checkpoint_time": "2026-02-12T08:00:00+01:00",
      "last_checkpoint_location": "ROSANOW, PL, Poland",
      "updated_at": "2026-02-16T00:42:37+00:00"
    },
    {
      "tracking_number": "0053038324474W",
      "carrier_slug": "dpd",
      "courier_name": "DPD",
      "status_tag": "Delivered",
      "title": "0053038324474W",
      "order_id": "6001601571",
      "sales_office_id": "",
      "source": "csv_importer",
      "custom_fields": {
        "courier": "dpd ",
        "custom_1": "returns_dpd"
      },
      "last_checkpoint_id": "",
      "last_checkpoint_time": "2026-02-12T08:00:00+01:00",
      "last_checkpoint_location": "ROSANOW, PL, Poland",
      "updated_at": "2026-02-16T00:42:45+00:00"
    },
    {
      "tracking_number": "0053044965840W",
      "carrier_slug": "dpd",
      "courier_name": "DPD",
      "status_tag": "Delivered",
      "title": "0053044965840W",
      "order_id": "6001602576",
      "sales_office_id": "",
      "source": "csv_importer",
      "custom_fields": {
        "courier": "dpd ",
        "custom_1": "returns_dpd"
      },
      "last_checkpoint_id": "",
      "last_checkpoint_time": "2026-02-13T07:35:00+01:00",
      "last_checkpoint_location": "ROSANOW, PL, Poland",
      "updated_at": "2026-02-16T05:12:43+00:00"
    },
    {
      "tracking_number": "0053045249119W",
      "carrier_slug": "dpd",
      "courier_name": "DPD",
      "status_tag": "Delivered",
      "title": "0053045249119W",
      "order_id": "6001602612",
      "sales_office_id": "",
      "source": "csv_importer",
      "custom_fields": {
        "courier": "dpd ",
        "custom_1": "returns_dpd"
      },
      "last_checkpoint_id": "",
      "last_checkpoint_time": "2026-02-11T09:00:00+01:00",
      "last_checkpoint_location": "ROSANOW, PL, Poland",
      "updated_at": "2026-02-16T00:42:38+00:00"
    },
    {
      "tracking_number": "0053048166282W",
      "carrier_slug": "dpd",
      "courier_name": "DPD",
      "status_tag": "Delivered",
      "title": "0053048166282W",
      "order_id": "6001605034",
      "sales_office_id": "",
      "source": "csv_importer",
      "custom_fields": {
        "courier": "dpd ",
        "custom_1": "returns_dpd"
      },
      "last_checkpoint_id": "",
      "last_checkpoint_time": "2026-02-12T08:00:00+01:00",
      "last_checkpoint_location": "ROSANOW, PL, Poland",
      "updated_at": "2026-02-16T00:42:39+00:00"
    },
    {
      "tracking_number": "0053047932671W",
      "carrier_slug": "dpd",
      "courier_name": "DPD",
      "status_tag": "Delivered",
      "title": "0053047932671W",
      "order_id": "6001604708",
      "sales_office_id": "",
      "source": "csv_importer",
      "custom_fields": {
        "courier": "dpd ",
        "custom_1": "returns_dpd"
      },
      "last_checkpoint_id": "",
      "last_checkpoint_time": "2026-02-12T08:00:00+01:00",
      "last_checkpoint_location": "ROSANOW, PL, Poland",
      "updated_at": "2026-02-16T00:42:38+00:00"
    },
    {
      "tracking_number": "0053050860470W",
      "carrier_slug": "dpd",
      "courier_name": "DPD",
      "status_tag": "Delivered",
      "title": "0053050860470W",
      "order_id": "6001606312",
      "sales_office_id": "",
      "source": "csv_importer",
      "custom_fields": {
        "courier": "dpd ",
        "custom_1": "returns_dpd"
      },
      "last_checkpoint_id": "",
      "last_checkpoint_time": "2026-02-11T14:54:01+01:00",
      "last_checkpoint_location": "Opole, PL, Poland",
      "updated_at": "2026-02-16T00:42:45+00:00"
    },
    {
      "tracking_number": "0053046950395W",
      "carrier_slug": "dpd",
      "courier_name": "DPD",
      "status_tag": "Delivered",
      "title": "0053046950395W",
      "order_id": "6001603103",
      "sales_office_id": "",
      "source": "csv_importer",
      "custom_fields": {
        "courier": "dpd ",
        "custom_1": "returns_dpd"
      },
      "last_checkpoint_id": "",
      "last_checkpoint_time": "2026-02-11T10:35:27+01:00",
      "last_checkpoint_location": "Wroclaw, PL, Poland",
      "updated_at": "2026-02-16T00:42:39+00:00"
    },
    {
      "tracking_number": "0053044912175W",
      "carrier_slug": "dpd",
      "courier_name": "DPD",
      "status_tag": "Delivered",
      "title": "0053044912175W",
      "order_id": "6001602555",
      "sales_office_id": "",
      "source": "csv_importer",
      "custom_fields": {
        "courier": "dpd ",
        "custom_1": "returns_dpd"
      },
      "last_checkpoint_id": "",
      "last_checkpoint_time": "2026-02-12T08:00:00+01:00",
      "last_checkpoint_location": "ROSANOW, PL, Poland",
      "updated_at": "2026-02-16T00:42:38+00:00"
    },
    {
      "tracking_number": "0053039621724W",
      "carrier_slug": "dpd",
      "courier_name": "DPD",
      "status_tag": "Delivered",
      "title": "0053039621724W",
      "order_id": "6001601926",
      "sales_office_id": "",
      "source": "csv_importer",
      "custom_fields": {
        "courier": "dpd ",
        "custom_1": "returns_dpd"
      },
      "last_checkpoint_id": "",
      "last_checkpoint_time": "2026-02-11T09:00:00+01:00",
      "last_checkpoint_location": "ROSANOW, PL, Poland",
      "updated_at": "2026-02-16T00:42:39+00:00"
    },
    {
      "tracking_number": "0053046468910W",
      "carrier_slug": "dpd",
      "courier_name": "DPD",
      "status_tag": "Delivered",
      "title": "0053046468910W",
      "order_id": "6001602961",
      "sales_office_id": "",
      "source": "csv_importer",
      "custom_fields": {
        "courier": "dpd ",
        "custom_1": "returns_dpd"
      },
      "last_checkpoint_id": "",
      "last_checkpoint_time": "2026-02-12T08:00:00+01:00",
      "last_checkpoint_location": "ROSANOW, PL, Poland",
      "updated_at": "2026-02-16T00:42:41+00:00"
    },
    {
      "tracking_number": "0053045249078W",
      "carrier_slug": "dpd",
      "courier_name": "DPD",
      "status_tag": "Delivered",
      "title": "0053045249078W",
      "order_id": "6001602612",
      "sales_office_id": "",
      "source": "csv_importer",
      "custom_fields": {
        "courier": "dpd ",
        "custom_1": "returns_dpd"
      },
      "last_checkpoint_id": "",
      "last_checkpoint_time": "2026-02-11T09:00:00+01:00",
      "last_checkpoint_location": "ROSANOW, PL, Poland",
      "updated_at": "2026-02-16T00:42:39+00:00"
    },
    {
      "tracking_number": "0053039018154W",
      "carrier_slug": "dpd",
      "courier_name": "DPD",
      "status_tag": "Delivered",
      "title": "0053039018154W",
      "order_id": "6001602088",
      "sales_office_id": "",
      "source": "csv_importer",
      "custom_fields": {
        "courier": "dpd ",
        "custom_1": "returns_dpd"
      },
      "last_checkpoint_id": "",
      "last_checkpoint_time": "2026-02-11T09:00:00+01:00",
      "last_checkpoint_location": "ROSANOW, PL, Poland",
      "updated_at": "2026-02-16T00:42:38+00:00"
    },
    {
      "tracking_number": "0053061265506W",
      "carrier_slug": "dpd",
      "courier_name": "DPD",
      "status_tag": "Delivered",
      "title": "0053061265506W",
      "order_id": "6001609793",
      "sales_office_id": "",
      "source": "csv_importer",
      "custom_fields": {
        "courier": "dpd ",
        "custom_1": "returns_dpd"
      },
      "last_checkpoint_id": "",
      "last_checkpoint_time": "2026-02-13T07:35:00+01:00",
      "last_checkpoint_location": "ROSANOW, PL, Poland",
      "updated_at": "2026-02-16T04:42:42+00:00"
    },
    {
      "tracking_number": "0053062897920W",
      "carrier_slug": "dpd",
      "courier_name": "DPD",
      "status_tag": "Delivered",
      "title": "0053062897920W",
      "order_id": "6001610434",
      "sales_office_id": "",
      "source": "csv_importer",
      "custom_fields": {
        "courier": "dpd ",
        "custom_1": "returns_dpd"
      },
      "last_checkpoint_id": "",
      "last_checkpoint_time": "2026-02-13T07:35:00+01:00",
      "last_checkpoint_location": "ROSANOW, PL, Poland",
      "updated_at": "2026-02-16T04:42:41+00:00"
    },
    {
      "tracking_number": "0053058966088W",
      "carrier_slug": "dpd",
      "courier_name": "DPD",
      "status_tag": "Delivered",
      "title": "0053058966088W",
      "order_id": "6001607168",
      "sales_office_id": "",
      "source": "csv_importer",
      "custom_fields": {
        "courier": "dpd ",
        "custom_1": "returns_dpd"
      },
      "last_checkpoint_id": "",
      "last_checkpoint_time": "2026-02-13T07:35:00+01:00",
      "last_checkpoint_location": "ROSANOW, PL, Poland",
      "updated_at": "2026-02-16T04:42:42+00:00"
    },
    {
      "tracking_number": "0053060402808W",
      "carrier_slug": "dpd",
      "courier_name": "DPD",
      "status_tag": "Delivered",
      "title": "0053060402808W",
      "order_id": "6001609086",
      "sales_office_id": "",
      "source": "csv_importer",
      "custom_fields": {
        "courier": "dpd ",
        "custom_1": "returns_dpd"
      },
      "last_checkpoint_id": "",
      "last_checkpoint_time": "2026-02-12T08:00:00+01:00",
      "last_checkpoint_location": "ROSANOW, PL, Poland",
      "updated_at": "2026-02-16T00:42:37+00:00"
    },
    {
      "tracking_number": "0053058965988W",
      "carrier_slug": "dpd",
      "courier_name": "DPD",
      "status_tag": "Delivered",
      "title": "0053058965988W",
      "order_id": "6001607168",
      "sales_office_id": "",
      "source": "csv_importer",
      "custom_fields": {
        "courier": "dpd ",
        "custom_1": "returns_dpd"
      },
      "last_checkpoint_id": "",
      "last_checkpoint_time": "2026-02-13T07:35:00+01:00",
      "last_checkpoint_location": "ROSANOW, PL, Poland",
      "updated_at": "2026-02-16T04:42:44+00:00"
    },
    {
      "tracking_number": "0053060355847W",
      "carrier_slug": "dpd",
      "courier_name": "DPD",
      "status_tag": "Delivered",
      "title": "0053060355847W",
      "order_id": "6001608580",
      "sales_office_id": "",
      "source": "csv_importer",
      "custom_fields": {
        "courier": "dpd ",
        "custom_1": "returns_dpd"
      },
      "last_checkpoint_id": "",
      "last_checkpoint_time": "2026-02-12T11:28:26+01:00",
      "last_checkpoint_location": "Warszawa, PL, Poland",
      "updated_at": "2026-02-16T00:42:41+00:00"
    },
    {
      "tracking_number": "0053058992123W",
      "carrier_slug": "dpd",
      "courier_name": "DPD",
      "status_tag": "Delivered",
      "title": "0053058992123W",
      "order_id": "6001607185",
      "sales_office_id": "",
      "source": "csv_importer",
      "custom_fields": {
        "courier": "dpd ",
        "custom_1": "returns_dpd"
      },
      "last_checkpoint_id": "",
      "last_checkpoint_time": "2026-02-10T16:44:30+01:00",
      "last_checkpoint_location": "Lisia Gora, PL, Poland",
      "updated_at": "2026-02-16T00:42:38+00:00"
    },
    {
      "tracking_number": "0053053133465W",
      "carrier_slug": "dpd",
      "courier_name": "DPD",
      "status_tag": "Delivered",
      "title": "0053053133465W",
      "order_id": "6001606646",
      "sales_office_id": "",
      "source": "csv_importer",
      "custom_fields": {
        "courier": "dpd ",
        "custom_1": "returns_dpd"
      },
      "last_checkpoint_id": "",
      "last_checkpoint_time": "2026-02-11T15:06:06+01:00",
      "last_checkpoint_location": "Lublin, PL, Poland",
      "updated_at": "2026-02-16T00:42:38+00:00"
    },
    {
      "tracking_number": "0053052466966W",
      "carrier_slug": "dpd",
      "courier_name": "DPD",
      "status_tag": "Delivered",
      "title": "0053052466966W",
      "order_id": "6001606505",
      "sales_office_id": "",
      "source": "csv_importer",
      "custom_fields": {
        "courier": "dpd ",
        "custom_1": "returns_dpd"
      },
      "last_checkpoint_id": "",
      "last_checkpoint_time": "2026-02-13T11:30:09+01:00",
      "last_checkpoint_location": "Konin, PL, Poland",
      "updated_at": "2026-02-16T04:42:42+00:00"
    },
    {
      "tracking_number": "0053062574754W",
      "carrier_slug": "dpd",
      "courier_name": "DPD",
      "status_tag": "Delivered",
      "title": "0053062574754W",
      "order_id": "6001610286",
      "sales_office_id": "",
      "source": "csv_importer",
      "custom_fields": {
        "courier": "dpd ",
        "custom_1": "returns_dpd"
      },
      "last_checkpoint_id": "",
      "last_checkpoint_time": "2026-02-12T12:37:14+01:00",
      "last_checkpoint_location": "Krakow, PL, Poland",
      "updated_at": "2026-02-16T00:42:38+00:00"
    }
  ]
}